realerikrani/sopenqlite/__init__.py
realerikrani/sopenqlite/db.py
realerikrani/sopenqlite/py.typed
realerikrani_sopenqlite-1.0.0.dist-info/LICENSE
realerikrani_sopenqlite-1.0.0.dist-info/METADATA
realerikrani_sopenqlite-1.0.0.dist-info/WHEEL
realerikrani_sopenqlite-1.0.0.dist-info/top_level.txt
realerikrani_sopenqlite-1.0.0.dist-info/RECORD
