Metadata-Version: 2.1
Name: realerikrani-sopenqlite
Version: 1.0.0
Summary: A brief description of your package
License: Apache-2.0
Project-URL: Repository, https://github.com/realerikrani/sopenqlite
Requires-Python: >=3.10
License-File: LICENSE
